syntrix/__init__.py
syntrix/cli_config.py
syntrix/cli_eval.py
syntrix/cli_sample.py
syntrix/cli_train.py
syntrix/train.py
syntrix/data/bpe.py
syntrix/data/collate.py
syntrix/data/download.py
syntrix/data/mmap.py
syntrix/data/text.py
syntrix/models/gpt_mini.py
syntrix/models/rnn_mini.py
syntrix/models/ssm_mini.py
syntrix/nn/attention.py
syntrix/nn/layers.py
syntrix/nn/rnn.py
syntrix/nn/ssm.py
syntrix/optim/__init__.py
syntrix/optim/ema.py
syntrix/optim/schedule.py
syntrix/utils/config.py
syntrix/utils/profiler.py
syntrix/utils/seed.py
syntrix-0.3.1.dist-info/licenses/LICENSE
syntrix-0.3.1.dist-info/METADATA
syntrix-0.3.1.dist-info/WHEEL
syntrix-0.3.1.dist-info/entry_points.txt
syntrix-0.3.1.dist-info/top_level.txt
syntrix-0.3.1.dist-info/RECORD
