Metadata-Version: 2.4
Name: syntrix
Version: 0.3.1
Summary: Syntrix-Base: CPU-first ML framework with tiny models and deterministic training
Author: Adrian Paredez
License-Expression: LicenseRef-MIT-Commons-Clause
Project-URL: Homepage, https://github.com/paredezadrian/syntrix-base
Project-URL: Repository, https://github.com/paredezadrian/syntrix-base
Classifier: Operating System :: OS Independent
Classifier: Programming Language :: Python
Classifier: Programming Language :: Python :: 3
Classifier: Programming Language :: Python :: 3.9
Classifier: Programming Language :: Python :: 3.10
Classifier: Programming Language :: Python :: 3.11
Classifier: Programming Language :: Python :: 3.12
Requires-Python: >=3.9
License-File: LICENSE
Requires-Dist: torch>=2.1.0
Requires-Dist: PyYAML>=6.0
Requires-Dist: numpy>=1.23
Dynamic: license-file
